README.md
setup.py
calculatortbalse/__init__.py
calculatortbalse/calculator.py
calculatortbalse.egg-info/PKG-INFO
calculatortbalse.egg-info/SOURCES.txt
calculatortbalse.egg-info/dependency_links.txt
calculatortbalse.egg-info/not-zip-safe
calculatortbalse.egg-info/top_level.txt
calculatortbalse/tests/__init__.py
calculatortbalse/tests/test_calculator.py
calculatortbalse/tests/__init__.py
calculatortbalse/tests/test_calculator.py