Metadata-Version: 2.1
Name: calculatortbalse
Version: 1.2
Summary: Calculator for Python Mastery project
Author: Vienmarskinis
